pyNewsApi.py
pyNewsApi-0.0.4.dist-info/METADATA
pyNewsApi-0.0.4.dist-info/WHEEL
pyNewsApi-0.0.4.dist-info/top_level.txt
pyNewsApi-0.0.4.dist-info/RECORD
