Metadata-Version: 2.1
Name: pyNewsApi
Version: 0.0.4
Summary: This module returns Latest News by category
Home-page: https://github.com/Ammyy9908/pyNews
Author: Sumit
Author-email: sb78639@gmail.com
License: GNU General Public License v2 or later (GPLv2+)
Platform: UNKNOWN
Classifier: Programming Language :: Python :: 3
Classifier: Programming Language :: Python :: 3.6
Classifier: Programming Language :: Python :: 3.7
Classifier: Programming Language :: Python :: 3.8
Classifier: License :: OSI Approved :: GNU General Public License v2 or later (GPLv2+)
Classifier: Operating System :: OS Independent
Requires-Dist: requests
Provides-Extra: dev
Requires-Dist: pytest (>=3.7) ; extra == 'dev'
